{
  "date": "2026-07-06",
  "label": "06/07/2026",
  "previousDate": "2026-07-03",
  "sourceDates": {
    "debentures": "2026-07-03",
    "cap12431": "2026-07-06",
    "capTrad": "2026-07-06",
    "perf12431": "2026-07-06",
    "perfTrad": "2026-07-06",
    "anbima": "2026-07-06",
    "blc": "2026-07-06",
    "fundos": "2026-07-06"
  },
  "summary": [
    {
      "texto": "Captação líquida Incentivados: −R$ 770 mi",
      "tom": "neg"
    },
    {
      "texto": "Captação líquida Tradicional: −R$ 779 mi",
      "tom": "neg"
    },
    {
      "texto": "Maior captação: Kinea (+R$ 14 mi)",
      "tom": "pos"
    },
    {
      "texto": "Maior resgate: ITAU Tsy (−R$ 414 mi)",
      "tom": "neg"
    },
    {
      "texto": "ANBIMA: 15 abertura(s) e 15 fechamento(s) de spread (bps)"
    },
    {
      "texto": "1 alerta(s) de qualidade",
      "tom": "warn"
    }
  ],
  "sections": {
    "debentures": {
      "novas": [],
      "saidas": [],
      "temSnapshotAnterior": false
    },
    "captacao": {
      "12431": {
        "dia": "2026-07-06",
        "captacao": 131016585.81000002,
        "resgate": 901079677.92,
        "liquido": -770063092.1099999,
        "pl": 333015680290.81995,
        "numFundos": 1605,
        "curados": 1632,
        "fechados": 283,
        "anterior": {
          "dia": "2026-07-03",
          "captacao": 149555391.71999997,
          "resgate": 281194537.96999997,
          "liquido": -131639146.25,
          "pl": 334759354874.70013,
          "numFundos": 1607
        }
      },
      "trad": {
        "dia": "2026-07-06",
        "captacao": 1706566239.7200003,
        "resgate": 2485136384.82,
        "liquido": -778570145.0999999,
        "pl": 1078624543822.57,
        "numFundos": 807,
        "curados": 827,
        "fechados": 29,
        "anterior": {
          "dia": "2026-07-03",
          "captacao": 1301862634.8099997,
          "resgate": 1610334661.6,
          "liquido": -308472026.7900002,
          "pl": 1081779413712.7402,
          "numFundos": 817
        }
      }
    },
    "gestores": {
      "top12431Captacao": [
        {
          "gestor": "Kinea",
          "captacao": 15083200,
          "resgate": 967866.8,
          "liquido": 14115333.2,
          "pl": 14105857054.12
        },
        {
          "gestor": "G5",
          "captacao": 2650000,
          "resgate": 0,
          "liquido": 2650000,
          "pl": 2253787679.55
        },
        {
          "gestor": "Rafter",
          "captacao": 502289.33,
          "resgate": 0,
          "liquido": 502289.33,
          "pl": 340941081.23
        },
        {
          "gestor": "Daycoval",
          "captacao": 263643.02,
          "resgate": 67730.05,
          "liquido": 195912.97000000003,
          "pl": 417905559.51
        },
        {
          "gestor": "ASA",
          "captacao": 81768.89,
          "resgate": 0,
          "liquido": 81768.89,
          "pl": 94995225.89
        }
      ],
      "top12431Resgate": [
        {
          "gestor": "ITAU Tsy",
          "captacao": 0,
          "resgate": 414275697.47,
          "liquido": -414275697.47,
          "pl": 27911582731.86
        },
        {
          "gestor": "BRAM",
          "captacao": 37242024.73,
          "resgate": 118629177.4,
          "liquido": -81387152.67000002,
          "pl": 28214232279.9
        },
        {
          "gestor": "BB Asset",
          "captacao": 9144560.63,
          "resgate": 67946737.8,
          "liquido": -58802177.169999994,
          "pl": 20020728722.2
        },
        {
          "gestor": "IAM",
          "captacao": 20083197.26,
          "resgate": 77673722.17,
          "liquido": -57590524.91,
          "pl": 83553425015.71
        },
        {
          "gestor": "SAM",
          "captacao": 1605160,
          "resgate": 27462140.01,
          "liquido": -25856980.01,
          "pl": 10579907874.92
        }
      ],
      "topTradCaptacao": [
        {
          "gestor": "Rio Bravo",
          "captacao": 150372338.78,
          "resgate": 77236.44,
          "liquido": 150295102.34,
          "pl": 319544723.63
        },
        {
          "gestor": "BB Asset",
          "captacao": 678707532.5,
          "resgate": 589582908.47,
          "liquido": 89124624.02999997,
          "pl": 209900176618.48
        },
        {
          "gestor": "Regia",
          "captacao": 50469224.75,
          "resgate": 5453128.08,
          "liquido": 45016096.67,
          "pl": 16939632903.35
        },
        {
          "gestor": "Daycoval",
          "captacao": 45308407.13,
          "resgate": 3951375.37,
          "liquido": 41357031.760000005,
          "pl": 3772665974.46
        },
        {
          "gestor": "Occam",
          "captacao": 32775702.02,
          "resgate": 6251720.6,
          "liquido": 26523981.42,
          "pl": 6413563106.42
        }
      ],
      "topTradResgate": [
        {
          "gestor": "XPG",
          "captacao": 44085391.01,
          "resgate": 515655650.35,
          "liquido": -471570259.34000003,
          "pl": 15229524571.79
        },
        {
          "gestor": "SAM",
          "captacao": 24073748.58,
          "resgate": 188571525.17,
          "liquido": -164497776.58999997,
          "pl": 45367464138.96
        },
        {
          "gestor": "Vinland",
          "captacao": 539700,
          "resgate": 155297779.16,
          "liquido": -154758079.16,
          "pl": 3819930647.84
        },
        {
          "gestor": "IAM",
          "captacao": 94371579.88,
          "resgate": 179041597.27,
          "liquido": -84670017.39000002,
          "pl": 217558502428.25
        },
        {
          "gestor": "CEF Asset",
          "captacao": 35527870.13,
          "resgate": 90151312.95,
          "liquido": -54623442.82,
          "pl": 68533332819.43
        }
      ]
    },
    "anbima": {
      "aberturas": [
        {
          "ticker": "CSNAA1",
          "indexador": "DI + 1.6500%",
          "indexadorFamilia": "CDI+",
          "emissor": "COMPANHIA SIDERURGICA NACIONAL",
          "grupo": "CSN",
          "base": "CDI",
          "tipo": "cdi",
          "spreadAnteriorBps": 1726.69,
          "spreadAtualBps": 1790.8899999999999,
          "variacaoBps": 64.19999999999982,
          "fmtAnterior": "CDI + 17,27%",
          "fmtAtual": "CDI + 17,91%",
          "spreadAtual": "CDI + 17,91%",
          "durationAnos": 1.56,
          "status": "ok"
        },
        {
          "ticker": "CSNAC4",
          "indexador": "IPCA + 7.0000%",
          "indexadorFamilia": "IPCA+",
          "emissor": "COMPANHIA SIDERURGICA NACIONAL",
          "grupo": "CSN",
          "base": "B33",
          "tipo": "ipca",
          "spreadAnteriorBps": 902,
          "spreadAtualBps": 963,
          "variacaoBps": 61,
          "fmtAnterior": "B33 + 902 bps",
          "fmtAtual": "B33 + 963 bps",
          "spreadAtual": "B33 + 963 bps",
          "durationAnos": 5.89,
          "status": "ok"
        },
        {
          "ticker": "CSNAA4",
          "indexador": "IPCA + 6.5000%",
          "indexadorFamilia": "IPCA+",
          "emissor": "COMPANHIA SIDERURGICA NACIONAL",
          "grupo": "CSN",
          "base": "B30",
          "tipo": "ipca",
          "spreadAnteriorBps": 1910,
          "spreadAtualBps": 1967,
          "variacaoBps": 57,
          "fmtAnterior": "B30 + 1910 bps",
          "fmtAtual": "B30 + 1967 bps",
          "spreadAtual": "B30 + 1967 bps",
          "durationAnos": 3.19,
          "status": "ok"
        },
        {
          "ticker": "CEEBD1",
          "indexador": "Pré-Fixado 11.6692%",
          "indexadorFamilia": "Pré",
          "emissor": "CIA. DE ELETRIC. DO EST. DA BAHIA-COELBA",
          "grupo": "Neoenergia",
          "base": "Pré",
          "tipo": "yield",
          "spreadAnteriorBps": 1354.06,
          "spreadAtualBps": 1407.38,
          "variacaoBps": 53.320000000000164,
          "fmtAnterior": "13,54%",
          "fmtAtual": "14,07%",
          "spreadAtual": "14,07%",
          "durationAnos": 4.51,
          "status": "ok"
        },
        {
          "ticker": "RECV24",
          "indexador": "IPCA + 7.2833%",
          "indexadorFamilia": "IPCA+",
          "emissor": "PETRORECONCAVO S.A.",
          "grupo": "PetroReconcavo",
          "base": "B35",
          "tipo": "ipca",
          "spreadAnteriorBps": -25,
          "spreadAtualBps": 23,
          "variacaoBps": 48,
          "fmtAnterior": "B35 - 25 bps",
          "fmtAtual": "B35 + 23 bps",
          "spreadAtual": "B35 + 23 bps",
          "durationAnos": 6.33,
          "status": "ok"
        },
        {
          "ticker": "CSNAA5",
          "indexador": "IPCA + 6.8300%",
          "indexadorFamilia": "IPCA+",
          "emissor": "COMPANHIA SIDERURGICA NACIONAL",
          "grupo": "CSN",
          "base": "B32",
          "tipo": "ipca",
          "spreadAnteriorBps": 1094,
          "spreadAtualBps": 1137,
          "variacaoBps": 43,
          "fmtAnterior": "B32 + 1094 bps",
          "fmtAtual": "B32 + 1137 bps",
          "spreadAtual": "B32 + 1137 bps",
          "durationAnos": 4.79,
          "status": "ok"
        },
        {
          "ticker": "CSNAB5",
          "indexador": "IPCA + 6.9924%",
          "indexadorFamilia": "IPCA+",
          "emissor": "COMPANHIA SIDERURGICA NACIONAL",
          "grupo": "CSN",
          "base": "B35",
          "tipo": "ipca",
          "spreadAnteriorBps": 869,
          "spreadAtualBps": 903,
          "variacaoBps": 34,
          "fmtAnterior": "B35 + 869 bps",
          "fmtAtual": "B35 + 903 bps",
          "spreadAtual": "B35 + 903 bps",
          "durationAnos": 6.33,
          "status": "ok"
        },
        {
          "ticker": "CSNAB4",
          "indexador": "IPCA + 6.8000%",
          "indexadorFamilia": "IPCA+",
          "emissor": "COMPANHIA SIDERURGICA NACIONAL",
          "grupo": "CSN",
          "base": "B31",
          "tipo": "ipca",
          "spreadAnteriorBps": 1074,
          "spreadAtualBps": 1105,
          "variacaoBps": 31,
          "fmtAnterior": "B31 + 1074 bps",
          "fmtAtual": "B31 + 1105 bps",
          "spreadAtual": "B31 + 1105 bps",
          "durationAnos": 4.34,
          "status": "ok"
        },
        {
          "ticker": "SUMI37",
          "indexador": "IPCA + 8.0993%",
          "indexadorFamilia": "IPCA+",
          "emissor": "GIGA MAIS FIBRA TELECOMUNICACOES S.A.",
          "grupo": "Giga+",
          "base": "B32",
          "tipo": "ipca",
          "spreadAnteriorBps": 562,
          "spreadAtualBps": 593,
          "variacaoBps": 31,
          "fmtAnterior": "B32 + 562 bps",
          "fmtAtual": "B32 + 593 bps",
          "spreadAtual": "B32 + 593 bps",
          "durationAnos": 4.91,
          "status": "ok"
        },
        {
          "ticker": "ELPLA6",
          "indexador": "DI + 1.6400%",
          "indexadorFamilia": "CDI+",
          "emissor": "ELETROPAULO METROPOL. ELETR. DE S.P. S/A",
          "grupo": "Enel Brasil",
          "base": "CDI",
          "tipo": "cdi",
          "spreadAnteriorBps": 262.81,
          "spreadAtualBps": 291.46000000000004,
          "variacaoBps": 28.650000000000034,
          "fmtAnterior": "CDI + 2,63%",
          "fmtAtual": "CDI + 2,91%",
          "spreadAtual": "CDI + 2,91%",
          "durationAnos": 1.52,
          "status": "ok"
        },
        {
          "ticker": "ENAT23",
          "indexador": "Pré-Fixado 13.5733%",
          "indexadorFamilia": "Pré",
          "emissor": "BRAVA ENERGIA S.A.",
          "grupo": "Brava Energia",
          "base": "Pré",
          "tipo": "yield",
          "spreadAnteriorBps": 1485.3300000000002,
          "spreadAtualBps": 1513.75,
          "variacaoBps": 28.419999999999845,
          "fmtAnterior": "14,85%",
          "fmtAtual": "15,14%",
          "spreadAtual": "15,14%",
          "durationAnos": 3.14,
          "status": "ok"
        },
        {
          "ticker": "QUAL17",
          "indexador": "DI + 3.5000%",
          "indexadorFamilia": "CDI+",
          "emissor": "QUALICORP CONSULTORIA E CORRETORA DE SEGUROS S.A.",
          "grupo": "Qualicorp",
          "base": "CDI",
          "tipo": "cdi",
          "spreadAnteriorBps": 380.53,
          "spreadAtualBps": 408.35999999999996,
          "variacaoBps": 27.829999999999984,
          "fmtAnterior": "CDI + 3,81%",
          "fmtAtual": "CDI + 4,08%",
          "spreadAtual": "CDI + 4,08%",
          "durationAnos": 0.84,
          "status": "ok"
        },
        {
          "ticker": "AZZA12",
          "indexador": "DI + 1.2500%",
          "indexadorFamilia": "CDI+",
          "emissor": "AZZAS 2154 S.A.",
          "grupo": "Azzas",
          "base": "CDI",
          "tipo": "cdi",
          "spreadAnteriorBps": 151.47,
          "spreadAtualBps": 177.39000000000001,
          "variacaoBps": 25.920000000000016,
          "fmtAnterior": "CDI + 1,51%",
          "fmtAtual": "CDI + 1,77%",
          "spreadAtual": "CDI + 1,77%",
          "durationAnos": 2.73,
          "status": "ok"
        },
        {
          "ticker": "LVTC22",
          "indexador": "DI + 2.7000%",
          "indexadorFamilia": "CDI+",
          "emissor": "LIVETECH DA BAHIA INDUSTRIA E COMERCIO S/A",
          "grupo": "Livetech",
          "base": "CDI",
          "tipo": "cdi",
          "spreadAnteriorBps": 583.9699999999999,
          "spreadAtualBps": 606.97,
          "variacaoBps": 23.000000000000114,
          "fmtAnterior": "CDI + 5,84%",
          "fmtAtual": "CDI + 6,07%",
          "spreadAtual": "CDI + 6,07%",
          "durationAnos": 1.46,
          "status": "ok"
        },
        {
          "ticker": "CSNAA2",
          "indexador": "DI + 2.5000%",
          "indexadorFamilia": "CDI+",
          "emissor": "COMPANHIA SIDERURGICA NACIONAL",
          "grupo": "CSN",
          "base": "CDI",
          "tipo": "cdi",
          "spreadAnteriorBps": 1423.11,
          "spreadAtualBps": 1445.94,
          "variacaoBps": 22.830000000000155,
          "fmtAnterior": "CDI + 14,23%",
          "fmtAtual": "CDI + 14,46%",
          "spreadAtual": "CDI + 14,46%",
          "durationAnos": 0.87,
          "status": "ok"
        }
      ],
      "fechamentos": [
        {
          "ticker": "SAPRC1",
          "indexador": "DI + 1.9000%",
          "indexadorFamilia": "CDI+",
          "emissor": "COMPANHIA DE SANEAMENTO  DO PARANA - SANEPAR",
          "grupo": "Sanepar",
          "base": "CDI",
          "tipo": "cdi",
          "spreadAnteriorBps": 153.33,
          "spreadAtualBps": 113.6,
          "variacaoBps": -39.73000000000002,
          "fmtAnterior": "CDI + 1,53%",
          "fmtAtual": "CDI + 1,14%",
          "spreadAtual": "CDI + 1,14%",
          "durationAnos": 1.57,
          "status": "ok"
        },
        {
          "ticker": "SMFT18",
          "indexador": "DI + 1.9500%",
          "indexadorFamilia": "CDI+",
          "emissor": "SMARTFIT ESCOLA DE GINASTICA E DANCA S/A",
          "grupo": "Smart Fit",
          "base": "CDI",
          "tipo": "cdi",
          "spreadAnteriorBps": 132.95,
          "spreadAtualBps": 96.39,
          "variacaoBps": -36.55999999999999,
          "fmtAnterior": "CDI + 1,33%",
          "fmtAtual": "CDI + 0,96%",
          "spreadAtual": "CDI + 0,96%",
          "durationAnos": 2.9,
          "status": "ok"
        },
        {
          "ticker": "TUPY35",
          "indexador": "DI + 1.1800%",
          "indexadorFamilia": "CDI+",
          "emissor": "TUPY S/A",
          "grupo": "Tupy",
          "base": "CDI",
          "tipo": "cdi",
          "spreadAnteriorBps": 427.20000000000005,
          "spreadAtualBps": 395.67,
          "variacaoBps": -31.53000000000003,
          "fmtAnterior": "CDI + 4,27%",
          "fmtAtual": "CDI + 3,96%",
          "spreadAtual": "CDI + 3,96%",
          "durationAnos": 4.06,
          "status": "ok"
        },
        {
          "ticker": "TUPY15",
          "indexador": "DI + 0.8700%",
          "indexadorFamilia": "CDI+",
          "emissor": "TUPY S/A",
          "grupo": "Tupy",
          "base": "CDI",
          "tipo": "cdi",
          "spreadAnteriorBps": 353.71000000000004,
          "spreadAtualBps": 328.18,
          "variacaoBps": -25.53000000000003,
          "fmtAnterior": "CDI + 3,54%",
          "fmtAtual": "CDI + 3,28%",
          "spreadAtual": "CDI + 3,28%",
          "durationAnos": 2.35,
          "status": "ok"
        },
        {
          "ticker": "ORIG22",
          "indexador": "Pré-Fixado 15.6300%",
          "indexadorFamilia": "Pré",
          "emissor": "ORIGEM ENERGIA S.A.",
          "grupo": "Origem Energia",
          "base": "Pré",
          "tipo": "yield",
          "spreadAnteriorBps": 1724.21,
          "spreadAtualBps": 1699.97,
          "variacaoBps": -24.24000000000001,
          "fmtAnterior": "17,24%",
          "fmtAtual": "17,00%",
          "spreadAtual": "17,00%",
          "durationAnos": 4.24,
          "status": "ok"
        },
        {
          "ticker": "TEPA12",
          "indexador": "IPCA + 10.0924%",
          "indexadorFamilia": "IPCA+",
          "emissor": "BRASIL TECNOLOGIA E PARTICIPACAO S.A.",
          "grupo": "Brasil Tecnologia e Participacao",
          "base": "B29",
          "tipo": "ipca",
          "spreadAnteriorBps": 751,
          "spreadAtualBps": 729,
          "variacaoBps": -22,
          "fmtAnterior": "B29 + 751 bps",
          "fmtAtual": "B29 + 729 bps",
          "spreadAtual": "B29 + 729 bps",
          "durationAnos": 2.39,
          "status": "ok"
        },
        {
          "ticker": "ORIG21",
          "indexador": "Pré-Fixado 14.1500%",
          "indexadorFamilia": "Pré",
          "emissor": "ORIGEM ENERGIA S.A.",
          "grupo": "Origem Energia",
          "base": "Pré",
          "tipo": "yield",
          "spreadAnteriorBps": 1708.24,
          "spreadAtualBps": 1693.36,
          "variacaoBps": -14.88000000000011,
          "fmtAnterior": "17,08%",
          "fmtAtual": "16,93%",
          "spreadAtual": "16,93%",
          "durationAnos": 4.31,
          "status": "ok"
        },
        {
          "ticker": "VAMO17",
          "indexador": "DI + 2.1700%",
          "indexadorFamilia": "CDI+",
          "emissor": "VAMOS LOCACAO DE CAMINHOES MAQUINAS E EQUIPAMENTOS S.A.",
          "grupo": "Simpar",
          "base": "CDI",
          "tipo": "cdi",
          "spreadAnteriorBps": 349.15,
          "spreadAtualBps": 334.31,
          "variacaoBps": -14.839999999999975,
          "fmtAnterior": "CDI + 3,49%",
          "fmtAtual": "CDI + 3,34%",
          "spreadAtual": "CDI + 3,34%",
          "durationAnos": 1.72,
          "status": "ok"
        },
        {
          "ticker": "VAMO13",
          "indexador": "DI + 2.3000%",
          "indexadorFamilia": "CDI+",
          "emissor": "VAMOS LOCACAO DE CAMINHOES MAQUINAS E EQUIPAMENTOS S.A.",
          "grupo": "Simpar",
          "base": "CDI",
          "tipo": "cdi",
          "spreadAnteriorBps": 270.12,
          "spreadAtualBps": 256.25,
          "variacaoBps": -13.870000000000005,
          "fmtAnterior": "CDI + 2,70%",
          "fmtAtual": "CDI + 2,56%",
          "spreadAtual": "CDI + 2,56%",
          "durationAnos": 1.68,
          "status": "ok"
        },
        {
          "ticker": "CSAN15",
          "indexador": "DI + 2.4000%",
          "indexadorFamilia": "CDI+",
          "emissor": "COSAN S.A.",
          "grupo": "Cosan",
          "base": "CDI",
          "tipo": "cdi",
          "spreadAnteriorBps": 234.79999999999998,
          "spreadAtualBps": 221.60000000000002,
          "variacaoBps": -13.19999999999996,
          "fmtAnterior": "CDI + 2,35%",
          "fmtAtual": "CDI + 2,22%",
          "spreadAtual": "CDI + 2,22%",
          "durationAnos": 1.57,
          "status": "ok"
        },
        {
          "ticker": "TRPLA5",
          "indexador": "DI + 0.7300%",
          "indexadorFamilia": "CDI+",
          "emissor": "ISA ENERGIA BRASIL S.A.",
          "grupo": "ISA Energia",
          "base": "CDI",
          "tipo": "cdi",
          "spreadAnteriorBps": 70.06,
          "spreadAtualBps": 57.02,
          "variacaoBps": -13.04,
          "fmtAnterior": "CDI + 0,70%",
          "fmtAtual": "CDI + 0,57%",
          "spreadAtual": "CDI + 0,57%",
          "durationAnos": 2.21,
          "status": "ok"
        },
        {
          "ticker": "ELPLA5",
          "indexador": "IPCA + 4.2600%",
          "indexadorFamilia": "IPCA+",
          "emissor": "ELETROPAULO METROPOL. ELETR. DE S.P. S/A",
          "grupo": "Enel Brasil",
          "base": "B30",
          "tipo": "ipca",
          "spreadAnteriorBps": 397,
          "spreadAtualBps": 385,
          "variacaoBps": -12,
          "fmtAnterior": "B30 + 397 bps",
          "fmtAtual": "B30 + 385 bps",
          "spreadAtual": "B30 + 385 bps",
          "durationAnos": 3.37,
          "status": "ok"
        },
        {
          "ticker": "IPIPA5",
          "indexador": "IPCA + 6.9550%",
          "indexadorFamilia": "IPCA+",
          "emissor": "IPIRANGA  PRODUTOS DE PETROLEO S.A.",
          "grupo": "Ultrapar",
          "base": "B35",
          "tipo": "ipca",
          "spreadAnteriorBps": -21,
          "spreadAtualBps": -33,
          "variacaoBps": -12,
          "fmtAnterior": "B35 - 21 bps",
          "fmtAtual": "B35 - 33 bps",
          "spreadAtual": "B35 - 33 bps",
          "durationAnos": 6.27,
          "status": "ok"
        },
        {
          "ticker": "IGTAA3",
          "indexador": "DI + 0.4500%",
          "indexadorFamilia": "CDI+",
          "emissor": "IGUATEMI EMPRESA DE SHOPPING CENTERS S.A",
          "grupo": "Iguatemi",
          "base": "CDI",
          "tipo": "cdi",
          "spreadAnteriorBps": 62.67,
          "spreadAtualBps": 50.739999999999995,
          "variacaoBps": -11.930000000000007,
          "fmtAnterior": "CDI + 0,63%",
          "fmtAtual": "CDI + 0,51%",
          "spreadAtual": "CDI + 0,51%",
          "durationAnos": 2.87,
          "status": "ok"
        },
        {
          "ticker": "AEGE17",
          "indexador": "DI + 3.4000%",
          "indexadorFamilia": "CDI+",
          "emissor": "EQUIPAV SANEAMENTO S.A.",
          "grupo": "Equipav",
          "base": "CDI",
          "tipo": "cdi",
          "spreadAnteriorBps": 538.25,
          "spreadAtualBps": 526.78,
          "variacaoBps": -11.470000000000027,
          "fmtAnterior": "CDI + 5,38%",
          "fmtAtual": "CDI + 5,27%",
          "spreadAtual": "CDI + 5,27%",
          "durationAnos": 4.07,
          "status": "ok"
        }
      ],
      "atual": "2026-07-06",
      "anterior": "2026-07-03",
      "semAnterior": false
    },
    "fundos": {
      "novos": [],
      "removidos": [],
      "semAnterior": false
    },
    "perf": {
      "top12431Pos": [
        {
          "cnpj": "53075427000115",
          "nome": "KINEA INCENTIVADO RF CP LP FI FINANCEIRO FUNDO INCENT EM INV EM DEBÊN DE INFRAESTRUTURA - RESP LTDA",
          "gestor": "Kinea",
          "segmento": "12431",
          "retorno": 19.9647,
          "pl": 45613332.89
        },
        {
          "cnpj": "63942021000146",
          "nome": "OCCAM BB INFRA LINEAR FI FINANCEIRO RENDA FIXA INVESTIMENTO EM INFRAESTRUTURA - RESP LIMITADA",
          "gestor": "Occam",
          "segmento": "12431",
          "retorno": 7.337,
          "pl": 987312680.33
        },
        {
          "cnpj": "60775750000167",
          "nome": "G5 ALLOCATION II FUNDO INCENTIVADO DE INVESTIMENTO FINANCEIRO EM INFRAESTRUTURA RENDA FIXA",
          "gestor": "G5",
          "segmento": "12431",
          "retorno": 1.0121,
          "pl": 36540434.88
        },
        {
          "cnpj": "54200289000111",
          "nome": "SK8 FIF - CLASSE DE INVESTIMENTO RENDA FIXA INCENTIVADO DE INVESTIMENTO EM INFRAESTRUTURA",
          "gestor": "G5",
          "segmento": "12431",
          "retorno": 0.8088,
          "pl": 17380611.77
        },
        {
          "cnpj": "60675392000110",
          "nome": "FORTE FIF - CLASSE DE INVESTIMENTO RF INCENTIVADO DE INVESTIMENTO EM INFRA",
          "gestor": "BRAM",
          "segmento": "12431",
          "retorno": 0.7212,
          "pl": 93815802.62
        }
      ],
      "top12431Neg": [
        {
          "cnpj": "63138979000189",
          "nome": "SANTANDER PB PJ INVESTIMENTO EM INFRA RENDA FIXA - FIF RESP LIMITADA",
          "gestor": "San WM",
          "segmento": "12431",
          "retorno": -42.8533,
          "pl": 206007.91
        },
        {
          "cnpj": "63319624000196",
          "nome": "A1 CRÉDITO FIF INVESTIMENTO EM DEBÊNTURES DE INFRA CDI ATIVO RF CRED PRIV RESP LIMITADA",
          "gestor": "Asset 1",
          "segmento": "12431",
          "retorno": -4.2291,
          "pl": 12319724.36
        },
        {
          "cnpj": "63572496000198",
          "nome": "VINLAND DEBÊNTURE INCENTIVADO 3 FIF INC EM INV EM DEB DE INFRA RF ATIVO CRED PRIV LP RESP LIMITADA",
          "gestor": "Vinland",
          "segmento": "12431",
          "retorno": -3.4447,
          "pl": 15980787.47
        },
        {
          "cnpj": "63386988000199",
          "nome": "LEGACY CAPITAL ARKAN FIF FUNDO INCENTIVADO EM INVESTIMENTO EM DEB DE INFRA CDI RF RESP LIMITADA",
          "gestor": "Legacy",
          "segmento": "12431",
          "retorno": -2.5849,
          "pl": 552379198.26
        },
        {
          "cnpj": "52248139000152",
          "nome": "CAPITANIA INFRA RENDA 90 FUNDO INCENTIVADO DE INVESTIMENTO EM INFRAESTRUTURA RENDA FIXA CRÉDITO PRIV",
          "gestor": "Capitânia",
          "segmento": "12431",
          "retorno": -1.2192,
          "pl": 522699401.86
        }
      ],
      "topTradPos": [
        {
          "cnpj": "41881271000180",
          "nome": "TRANCOSO FUNDO DE INVESTIMENTO FINANCEIRO MULTIMERCADO",
          "gestor": "Inter",
          "segmento": "trad",
          "retorno": 0.4824,
          "pl": 46227794.93
        },
        {
          "cnpj": "41348601000177",
          "nome": "JVV PREV FUNDO DE INVESTIMENTO FINANCEIRO MULTIMERCADO",
          "gestor": "BTG WM",
          "segmento": "trad",
          "retorno": 0.4191,
          "pl": 25768468.55
        },
        {
          "cnpj": "50553108000180",
          "nome": "RAFTER ICATU PREVIDENCIÁRIO QUALIFICADO FI FINANCEIRO - CI MULT CRED PRIV - RESP LIMITADA",
          "gestor": "Rafter",
          "segmento": "trad",
          "retorno": 0.333,
          "pl": 25235096.11
        },
        {
          "cnpj": "63901833000143",
          "nome": "SAIUALA KINEA FIF - FUNDO INCENTIVADO EM INVESTIMENTO EM DEB DE INFRA RF CRED PRIV - RESP LIMITADA",
          "gestor": "Kinea",
          "segmento": "trad",
          "retorno": 0.3246,
          "pl": 20662172.99
        },
        {
          "cnpj": "63900709000163",
          "nome": "LIMA EVALDT KINEA FIF FI INCENTIVADO EM DEBÊNTURES DE INFRA RF CRED PRIV RESP LIMITADA",
          "gestor": "Kinea",
          "segmento": "trad",
          "retorno": 0.3213,
          "pl": 26148982.95
        }
      ],
      "topTradNeg": [
        {
          "cnpj": "57154741000144",
          "nome": "QUANTITAS FUNDO DE INVESTIMENTO FINANCEIRO RENDA FIXA FIJI CRÉDITO PRIVADO LONGO PRAZO RESP LIMITADA",
          "gestor": "Quantitas",
          "segmento": "trad",
          "retorno": -14.3906,
          "pl": 5188471.32
        },
        {
          "cnpj": "51168708000197",
          "nome": "FUNDO DE INVESTIMENTO FINANCEIRO MULTIMERCADO LT",
          "gestor": "BTG Asset",
          "segmento": "trad",
          "retorno": -1.8517,
          "pl": 1141524048.61
        },
        {
          "cnpj": "51977823000102",
          "nome": "CATTUS FUNDO DE INVESTIMENTO FINANCEIRO RENDA FIXA",
          "gestor": "Starboard",
          "segmento": "trad",
          "retorno": -1.6163,
          "pl": 37722915.06
        },
        {
          "cnpj": "57555092000193",
          "nome": "BTG PACTUAL BRASLIGHT EOS FUNDO DE INVESTIMENTO FINANCEIRO",
          "gestor": "BTG Asset",
          "segmento": "trad",
          "retorno": -1.6014,
          "pl": 69181372.06
        },
        {
          "cnpj": "53726108000122",
          "nome": "CL VI FUNDO DE INVESTIMENTO MULTIMERCADO",
          "gestor": "Springs",
          "segmento": "trad",
          "retorno": -1.2717,
          "pl": 16665290.22
        }
      ]
    },
    "inclusoes": {
      "novosDebentures": [],
      "novosBlc": [],
      "temSnapshotBlc": true
    },
    "alertas": [
      {
        "tipo": "blc-sem-cadastro",
        "texto": "70 ativo(s) no BLC sem correspondencia em Debentures.csv"
      }
    ],
    "emissoesCVM": null,
    "emissoresFaltantes": null
  }
}
